Test_1/__init__.py
Test_1/filohellow.py
filohellow-0.0.1.dist-info/LICENSE.txt
filohellow-0.0.1.dist-info/METADATA
filohellow-0.0.1.dist-info/WHEEL
filohellow-0.0.1.dist-info/top_level.txt
filohellow-0.0.1.dist-info/RECORD
