Metadata-Version: 2.1
Name: filohellow
Version: 0.0.1
Summary: Basic Hello
Home-page: UNKNOWN
Author: FiloPyfornia_91
Author-email: filippo.stefani91@gmail.com
License: UNKNOWN
Platform: UNKNOWN
Classifier: Development Status :: 1 - Planning
Classifier: Intended Audience :: Developers
Classifier: Programming Language :: Python :: 3
Classifier: Operating System :: Unix
Classifier: Operating System :: MacOS :: MacOS X
Classifier: Operating System :: Microsoft :: Windows
License-File: LICENSE.txt
